azure/mgmt/dependencymap/__init__.py
azure/mgmt/dependencymap/_client.py
azure/mgmt/dependencymap/_configuration.py
azure/mgmt/dependencymap/_model_base.py
azure/mgmt/dependencymap/_patch.py
azure/mgmt/dependencymap/_serialization.py
azure/mgmt/dependencymap/_version.py
azure/mgmt/dependencymap/py.typed
azure/mgmt/dependencymap/aio/__init__.py
azure/mgmt/dependencymap/aio/_client.py
azure/mgmt/dependencymap/aio/_configuration.py
azure/mgmt/dependencymap/aio/_patch.py
azure/mgmt/dependencymap/aio/operations/__init__.py
azure/mgmt/dependencymap/aio/operations/_operations.py
azure/mgmt/dependencymap/aio/operations/_patch.py
azure/mgmt/dependencymap/models/__init__.py
azure/mgmt/dependencymap/models/_enums.py
azure/mgmt/dependencymap/models/_models.py
azure/mgmt/dependencymap/models/_patch.py
azure/mgmt/dependencymap/operations/__init__.py
azure/mgmt/dependencymap/operations/_operations.py
azure/mgmt/dependencymap/operations/_patch.py
azure_mgmt_dependencymap-1.0.0b1.dist-info/LICENSE
azure_mgmt_dependencymap-1.0.0b1.dist-info/METADATA
azure_mgmt_dependencymap-1.0.0b1.dist-info/WHEEL
azure_mgmt_dependencymap-1.0.0b1.dist-info/top_level.txt
azure_mgmt_dependencymap-1.0.0b1.dist-info/RECORD
